setup.py
Logstah.egg-info/PKG-INFO
Logstah.egg-info/SOURCES.txt
Logstah.egg-info/dependency_links.txt
Logstah.egg-info/not-zip-safe
Logstah.egg-info/requires.txt
Logstah.egg-info/top_level.txt
logstah/__init__.py
logstah/main.py