Metadata-Version: 1.0
Name: Logstah
Version: 0.1
Summary: A generic logger with RethinkDB as the primary logstore.
Home-page: https://github.com/rudimk/logstah
Author: Rudraksh MK
Author-email: rudraksh.mk@gmail.com
License: MIT
Platform: UNKNOWN
